mula/Add.py
mula/__init__.py
mula/__main__.py
mula/actions.py
mula/credentials.py
mula/json_tools.py
mula/log.py
mula/moodle_api.py
mula/publish.py
mula/structure.py
mula/structure_loader.py
mula/task.py
mula/text.py
mula/update.py
mula/url_handler.py
mula/viewer.py
mula-1.6.1.dist-info/METADATA
mula-1.6.1.dist-info/WHEEL
mula-1.6.1.dist-info/entry_points.txt
mula-1.6.1.dist-info/RECORD
