Metadata-Version: 2.4
Name: mula
Version: 1.6.1
Summary: Add your description here
Author-email: David <sena.ufc@gmail.com>
License-Expression: MIT
Requires-Python: >=3.10
Requires-Dist: appdirs>=1.4.4
Requires-Dist: mechanicalsoup>=1.3.0
Requires-Dist: requests>=2.32.3
Requires-Dist: types-appdirs>=1.4.3.5
